{
    "name": "CountDown",
    "description": "",
    "dependencies": {
        "core": "*",
        "radio": "*",
        "microphone": "*"
    },
    "files": [
        "main.blocks",
        "main.ts",
        "README.md",
        "main.py"
    ],
    "testFiles": [
        "test.ts"
    ],
    "targetVersions": {
        "target": "4.0.9",
        "targetId": "microbit"
    },
    "supportedTargets": [
        "microbit"
    ],
    "preferredEditor": "pyprj",
    "yotta": {
        "config": {
            "microbit-dal": {
                "bluetooth": {
                    "open": 0,
                    "whitelist": 1,
                    "security_level": "SECURITY_MODE_ENCRYPTION_WITH_MITM"
                }
            }
        }
    }
}
